[{"html":"\n\t\t\t\t\t<h3>\n\t\t\t\t\t\t<span id=\"APIs\" class=\"offset-anchor\" ></span>\n\t\t\t\t\t\t<a href=\"develop#APIs\" class=\"anchor\" aria-hidden=\"true\"> <i class=\"las la-link\"></i> </a>\n\t\t\t\t\t\tAPIs\n\t\t\t\t\t</h3>\n\t\t\t\t\t<h4>\n\t\t\t\t\t\t<span id=\"Authentication\" class=\"offset-anchor\" ></span>\n\t\t\t\t\t\t<a href=\"develop#Authentication\" class=\"anchor\" aria-hidden=\"true\"> <i class=\"las la-link\"></i> </a>\n\t\t\t\t\t\tAuthentication\n\t\t\t\t\t</h4>\n\t\t\t\t\t<h4>\n\t\t\t\t\t\t<span id=\"Management\" class=\"offset-anchor\" ></span>\n\t\t\t\t\t\t<a href=\"develop#Management\" class=\"anchor\" aria-hidden=\"true\"> <i class=\"las la-link\"></i> </a>\n\t\t\t\t\t\tManagement\n\t\t\t\t\t</h4>\n\t\t\t\t\t<h4>\n\t\t\t\t\t\t<span id=\"Administration\" class=\"offset-anchor\" ></span>\n\t\t\t\t\t\t<a href=\"develop#Administration\" class=\"anchor\" aria-hidden=\"true\"> <i class=\"las la-link\"></i> </a>\n\t\t\t\t\t\tAdministration\n\t\t\t\t\t</h4>","metadata":{"title":"Overview","description":"…"},"subsections":[{"slug":"APIs","title":"APIs","level":3},{"slug":"Authentication","title":"Authentication","level":4},{"slug":"Management","title":"Management","level":4},{"slug":"Administration","title":"Administration","level":4}],"slug":"Overview","file":"00-overview.en.md"},{"html":"\n\t\t\t\t\t<h3>\n\t\t\t\t\t\t<span id=\"Auth_GRPC\" class=\"offset-anchor\" ></span>\n\t\t\t\t\t\t<a href=\"develop#Auth_GRPC\" class=\"anchor\" aria-hidden=\"true\"> <i class=\"las la-link\"></i> </a>\n\t\t\t\t\t\tAuth GRPC\n\t\t\t\t\t</h3>\n\t\t\t\t\t<h3>\n\t\t\t\t\t\t<span id=\"Auth_Rest\" class=\"offset-anchor\" ></span>\n\t\t\t\t\t\t<a href=\"develop#Auth_Rest\" class=\"anchor\" aria-hidden=\"true\"> <i class=\"las la-link\"></i> </a>\n\t\t\t\t\t\tAuth Rest\n\t\t\t\t\t</h3>","metadata":{"title":"Authentication API","description":"…"},"subsections":[{"slug":"Auth_GRPC","title":"Auth GRPC","level":3},{"slug":"Auth_Rest","title":"Auth Rest","level":3}],"slug":"Authentication_API","file":"01-authentication.en.md"},{"html":"\n\t\t\t\t\t<h3>\n\t\t\t\t\t\t<span id=\"Mgmt_GRPC\" class=\"offset-anchor\" ></span>\n\t\t\t\t\t\t<a href=\"develop#Mgmt_GRPC\" class=\"anchor\" aria-hidden=\"true\"> <i class=\"las la-link\"></i> </a>\n\t\t\t\t\t\tMgmt GRPC\n\t\t\t\t\t</h3>\n\t\t\t\t\t<h3>\n\t\t\t\t\t\t<span id=\"Mgmt_Rest\" class=\"offset-anchor\" ></span>\n\t\t\t\t\t\t<a href=\"develop#Mgmt_Rest\" class=\"anchor\" aria-hidden=\"true\"> <i class=\"las la-link\"></i> </a>\n\t\t\t\t\t\tMgmt Rest\n\t\t\t\t\t</h3>","metadata":{"title":"Management API","description":"…"},"subsections":[{"slug":"Mgmt_GRPC","title":"Mgmt GRPC","level":3},{"slug":"Mgmt_Rest","title":"Mgmt Rest","level":3}],"slug":"Management_API","file":"02-management.en.md"},{"html":"\n\t\t\t\t\t<h3>\n\t\t\t\t\t\t<span id=\"Admin_GRPC\" class=\"offset-anchor\" ></span>\n\t\t\t\t\t\t<a href=\"develop#Admin_GRPC\" class=\"anchor\" aria-hidden=\"true\"> <i class=\"las la-link\"></i> </a>\n\t\t\t\t\t\tAdmin GRPC\n\t\t\t\t\t</h3>\n\t\t\t\t\t<h3>\n\t\t\t\t\t\t<span id=\"Admin_Rest\" class=\"offset-anchor\" ></span>\n\t\t\t\t\t\t<a href=\"develop#Admin_Rest\" class=\"anchor\" aria-hidden=\"true\"> <i class=\"las la-link\"></i> </a>\n\t\t\t\t\t\tAdmin Rest\n\t\t\t\t\t</h3>","metadata":{"title":"Admin API","description":"…"},"subsections":[{"slug":"Admin_GRPC","title":"Admin GRPC","level":3},{"slug":"Admin_Rest","title":"Admin Rest","level":3}],"slug":"Admin_API","file":"03-administration.en.md"}]