[{"html":"","metadata":{"title":"Integration","description":"…"},"subsections":[],"slug":"Integration","file":"00-integration.en.md"},{"html":"\n\t\t\t\t\t<h3>\n\t\t\t\t\t\t<span id=\"Go\" class=\"offset-anchor\" ></span>\n\t\t\t\t\t\t<a href=\"develop#Go\" class=\"anchor\" aria-hidden=\"true\"> <i class=\"las la-link\"></i> </a>\n\t\t\t\t\t\tGo\n\t\t\t\t\t</h3><blockquote>\n<p>TBA</p>\n</blockquote>\n","metadata":{"title":"SDK","description":"…"},"subsections":[{"slug":"Go","title":"Go","level":3}],"slug":"SDK","file":"01-sdk.en.md"}]