[{"html":"\n\t\t\t\t\t<h3>\n\t\t\t\t\t\t<span id=\"Account_Creation\" class=\"offset-anchor\" ></span>\n\t\t\t\t\t\t<a href=\"manuals#Account_Creation\" class=\"anchor\" aria-hidden=\"true\"> <i class=\"las la-link\"></i> </a>\n\t\t\t\t\t\tAccount Creation\n\t\t\t\t\t</h3>\n\t\t\t\t\t<h3>\n\t\t\t\t\t\t<span id=\"Password_Change\" class=\"offset-anchor\" ></span>\n\t\t\t\t\t\t<a href=\"manuals#Password_Change\" class=\"anchor\" aria-hidden=\"true\"> <i class=\"las la-link\"></i> </a>\n\t\t\t\t\t\tPassword Change\n\t\t\t\t\t</h3>\n\t\t\t\t\t<h3>\n\t\t\t\t\t\t<span id=\"Password_Reset\" class=\"offset-anchor\" ></span>\n\t\t\t\t\t\t<a href=\"manuals#Password_Reset\" class=\"anchor\" aria-hidden=\"true\"> <i class=\"las la-link\"></i> </a>\n\t\t\t\t\t\tPassword Reset\n\t\t\t\t\t</h3>\n\t\t\t\t\t<h3>\n\t\t\t\t\t\t<span id=\"Multifactor_Setup\" class=\"offset-anchor\" ></span>\n\t\t\t\t\t\t<a href=\"manuals#Multifactor_Setup\" class=\"anchor\" aria-hidden=\"true\"> <i class=\"las la-link\"></i> </a>\n\t\t\t\t\t\tMultifactor Setup\n\t\t\t\t\t</h3>","metadata":{"title":"User Manual"},"subsections":[{"slug":"Account_Creation","title":"Account Creation","level":3},{"slug":"Password_Change","title":"Password Change","level":3},{"slug":"Password_Reset","title":"Password Reset","level":3},{"slug":"Multifactor_Setup","title":"Multifactor Setup","level":3}],"slug":"User_Manual","file":"00-user.en.md"},{"html":"\n\t\t\t\t\t<h3>\n\t\t\t\t\t\t<span id=\"Password_set_process_for_a_user\" class=\"offset-anchor\" ></span>\n\t\t\t\t\t\t<a href=\"manuals#Password_set_process_for_a_user\" class=\"anchor\" aria-hidden=\"true\"> <i class=\"las la-link\"></i> </a>\n\t\t\t\t\t\tPassword set process for a user\n\t\t\t\t\t</h3>","metadata":{"title":"Supporter"},"subsections":[{"slug":"Password_set_process_for_a_user","title":"Password set process for a user","level":3}],"slug":"Supporter","file":"01-supporter.en.md"},{"html":"\n\t\t\t\t\t<h3>\n\t\t\t\t\t\t<span id=\"Organisation_Creation\" class=\"offset-anchor\" ></span>\n\t\t\t\t\t\t<a href=\"manuals#Organisation_Creation\" class=\"anchor\" aria-hidden=\"true\"> <i class=\"las la-link\"></i> </a>\n\t\t\t\t\t\tOrganisation Creation\n\t\t\t\t\t</h3>\n\t\t\t\t\t<h3>\n\t\t\t\t\t\t<span id=\"Domain_Verification\" class=\"offset-anchor\" ></span>\n\t\t\t\t\t\t<a href=\"manuals#Domain_Verification\" class=\"anchor\" aria-hidden=\"true\"> <i class=\"las la-link\"></i> </a>\n\t\t\t\t\t\tDomain Verification\n\t\t\t\t\t</h3>\n\t\t\t\t\t<h3>\n\t\t\t\t\t\t<span id=\"Projekte_Creation\" class=\"offset-anchor\" ></span>\n\t\t\t\t\t\t<a href=\"manuals#Projekte_Creation\" class=\"anchor\" aria-hidden=\"true\"> <i class=\"las la-link\"></i> </a>\n\t\t\t\t\t\tProjekte Creation\n\t\t\t\t\t</h3>\n\t\t\t\t\t<h3>\n\t\t\t\t\t\t<span id=\"Permission_Management\" class=\"offset-anchor\" ></span>\n\t\t\t\t\t\t<a href=\"manuals#Permission_Management\" class=\"anchor\" aria-hidden=\"true\"> <i class=\"las la-link\"></i> </a>\n\t\t\t\t\t\tPermission Management\n\t\t\t\t\t</h3>","metadata":{"title":"Administrator"},"subsections":[{"slug":"Organisation_Creation","title":"Organisation Creation","level":3},{"slug":"Domain_Verification","title":"Domain Verification","level":3},{"slug":"Projekte_Creation","title":"Projekte Creation","level":3},{"slug":"Permission_Management","title":"Permission Management","level":3}],"slug":"Administrator","file":"02-admin.en.md"}]